PyDMXControl/_Colors.py
PyDMXControl/__init__.py
PyDMXControl/audio/_Player.py
PyDMXControl/audio/__init__.py
PyDMXControl/audio/requirements.txt
PyDMXControl/controllers/_Controller.py
PyDMXControl/controllers/_OpenDMXController.py
PyDMXControl/controllers/_PrintController.py
PyDMXControl/controllers/_SerialController.py
PyDMXControl/controllers/_TransmittingController.py
PyDMXControl/controllers/__init__.py
PyDMXControl/controllers/_uDMXController.py
PyDMXControl/controllers/utils/__init__.py
PyDMXControl/controllers/utils/debug.py
PyDMXControl/effects/__init__.py
PyDMXControl/effects/Color/_Chase.py
PyDMXControl/effects/Color/__init__.py
PyDMXControl/effects/Intensity/_Dim.py
PyDMXControl/effects/Intensity/__init__.py
PyDMXControl/effects/defaults/_Effect.py
PyDMXControl/effects/defaults/__init__.py
PyDMXControl/profiles/__init__.py
PyDMXControl/profiles/Eyourlife/_Small_Flat_Par.py
PyDMXControl/profiles/Eyourlife/__init__.py
PyDMXControl/profiles/Generic/_Custom.py
PyDMXControl/profiles/Generic/_Dimmer.py
PyDMXControl/profiles/Generic/_RGB_Vdim.py
PyDMXControl/profiles/Generic/__init__.py
PyDMXControl/profiles/Lixada/_LED_Mini_Par.py
PyDMXControl/profiles/Lixada/__init__.py
PyDMXControl/profiles/Pulse/_Compact_LED_PAR.py
PyDMXControl/profiles/Pulse/__init__.py
PyDMXControl/profiles/Showtec/_Compact_PAR.py
PyDMXControl/profiles/Showtec/__init__.py
PyDMXControl/profiles/Stairville/_LED_Par_10mm.py
PyDMXControl/profiles/Stairville/_LED_Par_36.py
PyDMXControl/profiles/Stairville/_Quad_Par_Profile.py
PyDMXControl/profiles/Stairville/__init__.py
PyDMXControl/profiles/defaults/_Fixture.py
PyDMXControl/profiles/defaults/_Vdim.py
PyDMXControl/profiles/defaults/__init__.py
PyDMXControl/profiles/funGeneration/_LED_Pot_12_RGBW.py
PyDMXControl/profiles/funGeneration/__init__.py
PyDMXControl/utils/_ExceptionThread.py
PyDMXControl/utils/__init__.py
PyDMXControl/utils/exceptions.py
PyDMXControl/utils/timing/_Ticker.py
PyDMXControl/utils/timing/_TimedEvent.py
PyDMXControl-2.0.0.dist-info/LICENSE
PyDMXControl-2.0.0.dist-info/METADATA
PyDMXControl-2.0.0.dist-info/WHEEL
PyDMXControl-2.0.0.dist-info/top_level.txt
PyDMXControl-2.0.0.dist-info/RECORD
