Metadata-Version: 2.1
Name: PyDMXControl
Version: 2.0.0
Summary: A Python 3 module to control DMX using OpenDMX or uDMX. Featuring fixture profiles, built-in effects and a web control panel.
Home-page: https://github.com/MattIPv4/PyDMXControl/
Author: Matt Cowley (MattIPv4)
Author-email: me@mattcowley.co.uk
License: GPLv3
Project-URL: Source, https://github.com/MattIPv4/PyDMXControl/tree/master
Project-URL: Funding, https://patreon.mattcowley.co.uk/
Project-URL: Issues, https://github.com/MattIPv4/PyDMXControl/issues
Project-URL: Discord, https://discord.mattcowley.co.uk/
Project-URL: Slack, https://slack.mattcowley.co.uk/
Keywords: lighting light lights fixtures fixture-profiles controller control control-dmx dmx dmx-512 dmx-interface dmx-channels dmx-dimmer dmx-library theatre udmx opendmx open-dmx ftdi
Classifier: License :: OSI Approved :: GNU General Public License v3 (GPLv3)
Classifier: Programming Language :: Python :: 3
Classifier: Programming Language :: Python :: 3.6
Classifier: Programming Language :: Python :: 3.7
Classifier: Programming Language :: Python :: 3.8
Classifier: Programming Language :: Python :: 3.9
Classifier: Programming Language :: Python :: 3.10
Classifier: Programming Language :: Python :: 3.11
Classifier: Development Status :: 5 - Production/Stable
Classifier: Intended Audience :: Developers
Classifier: Intended Audience :: Other Audience
Classifier: Environment :: Console
Classifier: Environment :: Web Environment
Classifier: Framework :: Flask
Classifier: Natural Language :: English
Classifier: Operating System :: OS Independent
Classifier: Topic :: Home Automation
Classifier: Topic :: Internet
Classifier: Topic :: Multimedia
Classifier: Topic :: Software Development :: Embedded Systems
Classifier: Topic :: Software Development :: Libraries :: Python Modules
Classifier: Topic :: Software Development :: User Interfaces
Requires-Python: >= 3.6
Provides-Extra: audio
License-File: LICENSE
